{
  "id": "vida-de-oracao-constante",
  "title": "A Vida de Oração Constante: O Exemplo de Daniel",
  "description": "Devocional sobre como cultivar uma vida de oração constante e inabalável, inspirado no exemplo do profeta Daniel",
  "category": "devocional",
  "author": "equipe-palavra-viva",
  "date": "2024-10-31",
  "tags": ["oração", "daniel", "fidelidade", "intimidade", "perseverança"],
  "progress": 0,
  "content_file": "vida-de-oracao-constante.md",
  "featured": true,
  "reading_time": 12,
  "difficulty": "intermediario",
  "bible_references": [
    "Daniel 6:10-23",
    "Daniel 9:3-19",
    "1 Tessalonicenses 5:17",
    "Salmo 5:3",
    "Salmo 55:17",
    "Romanos 12:11-12",
    "Filipenses 4:6",
    "Lucas 18:1"
  ],
  "related_studies": [],
  "version": "1.0.0",
  "last_updated": "2024-10-31T10:00:00Z",
  "status": "published",
  "views": 0,
  "favorites": 0
}